{
  "annotations": {},
  "nodes": [
    {
      "annotations": {
        "nodeData": {
          "id": "nodeData",
          "data": {
            "content": "var x = 1;",
            "type": "editor",
            "label": "Declaration",
            "language": "JavaScript",
            "width": 300,
            "height": 200
          }
        }
      },
      "id": "1",
      "content": "var x = 1;"
    },
    {
      "annotations": {
        "nodeData": {
          "id": "nodeData",
          "data": {
            "content": "x + 2;",
            "type": "editor",
            "label": "Usage",
            "language": "JavaScript",
            "width": 300,
            "height": 200
          }
        }
      },
      "id": "2",
      "content": "x + 2;"
    },
    {
      "annotations": {
        "nodeData": {
          "id": "nodeData",
          "data": {
            "content": "",
            "type": "editor",
            "label": "Result",
            "language": "JavaScript",
            "width": 300,
            "height": 200
          }
        }
      },
      "id": "3",
      "content": ""
    }
  ],
  "edgeTypes": [
    {
      "annotations": {},
      "id": "sequence",
      "priority": 8,
      "immediate": false
    },
    {
      "annotations": {},
      "id": "execute",
      "priority": 2,
      "immediate": false
    }
  ],
  "edges": [
    {
      "annotations": {},
      "edgeType": "sequence",
      "sourceNode": "1",
      "targetNode": "2"
    },
    {
      "annotations": {},
      "edgeType": "execute",
      "sourceNode": "2",
      "targetNode": "3"
    }
  ]
}
